autodata/__init__.py
autodata/autodata.py
autodata-0.12.dist-info/METADATA
autodata-0.12.dist-info/WHEEL
autodata-0.12.dist-info/top_level.txt
autodata-0.12.dist-info/RECORD
