Metadata-Version: 2.1
Name: autodata
Version: 0.12
Summary: Auto allocation dict and list
Home-page: https://github.com/shii4c/PythonAutoData
Author: Kenichiro SHII
Author-email: shii4c@gmail.com
License: MIT
Platform: UNKNOWN
Classifier: Programming Language :: Python :: 3 :: Only
Classifier: Topic :: Software Development :: Libraries :: Python Modules
Classifier: License :: OSI Approved :: MIT License
